teflo/__init__.py
teflo/_compat.py
teflo/ansible_helpers.py
teflo/cli.py
teflo/constants.py
teflo/core.py
teflo/exceptions.py
teflo/helpers.py
teflo/teflo.py
teflo/executors/__init__.py
teflo/executors/execute_manager.py
teflo/executors/ext/__init__.py
teflo/executors/ext/ansible_executor_plugin/__init__.py
teflo/executors/ext/ansible_executor_plugin/ansible_executor_plugin.py
teflo/executors/ext/ansible_executor_plugin/files/extensions.py
teflo/executors/ext/ansible_executor_plugin/files/schema.yml
teflo/files/extensions.py
teflo/files/schema.yml
teflo/importers/__init__.py
teflo/importers/artifact_importer.py
teflo/notifiers/__init__.py
teflo/notifiers/notification_emitter.py
teflo/notifiers/ext/__init__.py
teflo/notifiers/ext/email/__init__.py
teflo/notifiers/ext/email/email_notification_plugin.py
teflo/notifiers/ext/email/schema/email_extensions.py
teflo/notifiers/ext/email/schema/schema.yml
teflo/notifiers/ext/email/templates/email_on_start_txt_template.jinja
teflo/notifiers/ext/email/templates/email_txt_template.jinja
teflo/orchestrators/__init__.py
teflo/orchestrators/action_orchestrator.py
teflo/orchestrators/ext/__init__.py
teflo/orchestrators/ext/ansible_orchestrator_plugin/__init__.py
teflo/orchestrators/ext/ansible_orchestrator_plugin/ansible_orchestrator_plugin.py
teflo/orchestrators/ext/ansible_orchestrator_plugin/files/extensions.py
teflo/orchestrators/ext/ansible_orchestrator_plugin/files/schema.yml
teflo/providers/__init__.py
teflo/providers/aws.py
teflo/providers/beaker.py
teflo/providers/libvirt.py
teflo/providers/openstack.py
teflo/provisioners/__init__.py
teflo/provisioners/asset_provisioner.py
teflo/provisioners/ext/__init__.py
teflo/provisioners/ext/bkr_client_plugin/__init__.py
teflo/provisioners/ext/bkr_client_plugin/beaker_client_plugin.py
teflo/provisioners/ext/bkr_client_plugin/extensions.py
teflo/provisioners/ext/bkr_client_plugin/schema.yml
teflo/provisioners/ext/os_libcloud_plugin/__init__.py
teflo-2.4.1.dist-info/AUTHORS
teflo-2.4.1.dist-info/LICENSE
teflo-2.4.1.dist-info/METADATA
teflo-2.4.1.dist-info/WHEEL
teflo-2.4.1.dist-info/entry_points.txt
teflo-2.4.1.dist-info/top_level.txt
teflo-2.4.1.dist-info/RECORD
