Metadata-Version: 2.1
Name: teflo
Version: 2.4.1
Summary: Test Execution Framework Libraries and Objects. It is an orchestration software that controls the flow of a set of testing scenarios.
Author: Red Hat Inc.
License: GPLv3
Classifier: Development Status :: 5 - Production/Stable
Classifier: Intended Audience :: Developers
Classifier: License :: OSI Approved :: GNU Lesser General Public License v3 (LGPLv3)
Classifier: Natural Language :: English
Classifier: Programming Language :: Python :: 3
Classifier: Programming Language :: Python :: 3 :: Only
Classifier: Programming Language :: Python :: 3.9
Requires-Python: >=3.9
License-File: LICENSE
License-File: AUTHORS
Requires-Dist: ansible >=2.14.0
Requires-Dist: apache-libcloud ==2.2.0
Requires-Dist: blaster >=0.3.0
Requires-Dist: Click >=6.7
Requires-Dist: ipaddress
Requires-Dist: Jinja2 >=2.10
Requires-Dist: pykwalify >=1.6.0
Requires-Dist: python-cachetclient
Requires-Dist: ruamel.yaml >=0.15.64
Requires-Dist: paramiko >=2.4.2
Requires-Dist: retry2 >=0.9.4
Requires-Dist: ssh-python >=0.9.0
Requires-Dist: requests >=2.20.1
Requires-Dist: urllib3 >=1.26
Requires-Dist: termcolor >=1.1.0
Provides-Extra: linchpin-wrapper
Requires-Dist: teflo-linchpin-plugin ; extra == 'linchpin-wrapper'
Provides-Extra: notify-service-plugin
Requires-Dist: teflo-notify-service-plugin ; extra == 'notify-service-plugin'
Provides-Extra: openstack-client-plugin
Requires-Dist: teflo-openstack-client-plugin ; extra == 'openstack-client-plugin'
Provides-Extra: terraform-plugin
Requires-Dist: teflo-terraform-plugin ; extra == 'terraform-plugin'
Provides-Extra: webhook-notification-plugin
Requires-Dist: teflo-webhooks-notification-plugin ; extra == 'webhook-notification-plugin'
